repofs/__init__.py
repofs/__main__.py
repofs/gitoper.py
repofs/repofs.py
repofs/utils.py
repofs/handlers/__init__.py
repofs/handlers/commit_date.py
repofs/handlers/commit_handler.py
repofs/handlers/commit_hash.py
repofs/handlers/handler_base.py
repofs/handlers/ref.py
repofs/handlers/root.py
repofs-0.2.4.data/data/man/man1/repofs.1
repofs-0.2.4.dist-info/DESCRIPTION.rst
repofs-0.2.4.dist-info/METADATA
repofs-0.2.4.dist-info/RECORD
repofs-0.2.4.dist-info/WHEEL
repofs-0.2.4.dist-info/entry_points.txt
repofs-0.2.4.dist-info/metadata.json
repofs-0.2.4.dist-info/top_level.txt
