Metadata-Version: 2.0
Name: repofs
Version: 0.2.4
Summary: File system view of git repositories
Home-page: https://github.com/AUEB-BALab/RepoFS
Author: UNKNOWN
Author-email: UNKNOWN
License: Apache Software License
Platform: UNKNOWN
Requires-Dist: fusepy
Requires-Dist: pygit2 (==0.24.2)
